[{"id": "burning_blood", "name": "Burning Blood", "desc": "At the end of combat, heal 6 HP.", "rarity": "Starter", "class": "Ironclad"}, {"id": "red_skull", "name": "Red Skull", "desc": "While your HP is at or below 50%, you have 3 additional Strength.", "rarity": "Common", "class": "Ironclad"}, {"id": "paper_phrog", "name": "Paper Phrog", "desc": "Enemies with Vulnerable take 75% more damage rather than 50%.", "rarity": "Uncommon", "class": "Ironclad"}, {"id": "self_forming_clay", "name": "Self-Forming Clay", "desc": "Whenever you lose HP in combat, gain 3 Block next turn.", "rarity": "Uncommon", "class": "Ironclad"}, {"id": "champion_belt", "name": "Champion Belt", "desc": "Whenever you apply Vulnerable, also apply 1 Weak.", "rarity": "Rare", "class": "Ironclad"}, {"id": "charon's_ashes", "name": "Charon's Ashes", "desc": "Whenever you Exhaust a card, deal 3 damage to ALL enemies.", "rarity": "Rare", "class": "Ironclad"}, {"id": "magic_flower", "name": "Magic Flower", "desc": "Healing is 50% more effective during combat.", "rarity": "Rare", "class": "Ironclad"}, {"id": "black_blood", "name": "Black Blood", "desc": "Replaces Burning Blood. At the end of combat, heal 12 HP.", "rarity": "Boss", "class": "Ironclad"}, {"id": "mark_of_pain", "name": "Mark of Pain", "desc": "Gain 1 Energy at the start of each turn. Start combats with 2 Wounds in your draw pile.", "rarity": "Boss", "class": "Ironclad"}, {"id": "runic_cube", "name": "Runic Cube", "desc": "Whenever you lose HP, draw 1 card.", "rarity": "Boss", "class": "Ironclad"}, {"id": "brimstone", "name": "Brimstone", "desc": "At the start of your turn, gain 2 Strength and ALL enemies gain 1 Strength.", "rarity": "Shop", "class": "Ironclad"}]